Ejercicio4.v
module Mux_2_1(input wire D_0, D_1, S_0, output wire Y);
	
	assign Y = S_0? D_1:D_0;
	
endmodule

module Mux_4_1(input wire D_0, D_1, D_2, D_3, S_0, S_1, output wire Y);

	wire Y1,Y2;
	
	Mux_2_1 D0(D_0, D_1, S_0, Y1);
	Mux_2_1 D1(D_2, D_3, S_0, Y2);
	Mux_2_1 Out(Y1, Y2, S_1, Y);

endmodule

module Mux_8_1(input wire D_0, D_1, D_2, D_3, D_4, D_5, D_6, D_7, S_0, S_1, S_2, output wire Y);
	
	wire Y1,Y2,Y3,Y4;
	
	Mux_2_1 D0(D_0, D_1, S_0, Y1);
	Mux_2_1 D1(D_2, D_3, S_0, Y2);
	Mux_2_1 D2(D_4, D_5, S_0, Y3);
	Mux_2_1 D3(D_6, D_7, S_0, Y4);
	Mux_4_1 Out(Y1, Y2, Y3, Y4, S_1, S_2, Y);

endmodule

module Tablal_Mux_8_1(input wire D_0, D_1, D_2, D_3, D_4, D_5, D_6, D_7, A, B, C, output wire Y);

	Mux_8_1 T1(D_0, D_1, D_2, D_3, D_4, D_5, D_6, D_7, C, B, A, Y);
 
endmodule

module Tabla2_Mux_8_1(input wire D_0, D_1, D_2, D_3, D_4, D_5, D_6, D_7, A, B, C, output wire Y);

	Mux_8_1 T2(D_0, D_1, D_2, D_3, D_4, D_5, D_6, D_7, C, B, A, Y);
 
endmodule

module Tablal_Mux_4_1(input wire A, B, C, output wire Y);

	wire NC;
	not (NC, C);
	Mux_4_1 T1(C, NC, NC, C, B, A, Y);
 
endmodule

module Tabla2_Mux_4_1(input wire DG, A, B, C, output wire Y);

	wire NC;
	not (NC, C);
	Mux_4_1 T2(NC, DG, C, NC, B, A, Y);
 
endmodule

module Tablal_Mux_2_1(input wire A, B, C, output wire Y);

	wire D0, D1;
	xor (D0, B, C);
	not (D1, D0);
	Mux_2_1 T1(D0, D1, A, Y);
 
endmodule

module Tabla2_Mux_2_1(input wire A, B, C, output wire Y);

	wire D0, D1;
	nor (D0, B, C);
	nand (D1, B, C);
	Mux_2_1 T2(D0, D1, A, Y);
 
endmodule

Ejercicio4_tb.v
module testbench();
	
	reg A, B, C;
	wire Y1, Y2, Y3, Y4, Y5, Y6, DG, DH;
	assign DG = 0;
	assign DH = 1;
	
	Tablal_Mux_8_1	T_1(DG, DH, DH, DG, DH, DG, DG, DH, A, B, C, Y1);
	Tabla2_Mux_8_1	T_2(DH, DG, DG, DG, DG, DH, DH, DG, A, B, C, Y2);
	Tablal_Mux_4_1  t_1(A, B, C, Y3);
	Tabla2_Mux_4_1  t_2(DG, A, B, C, Y4);
	Tablal_Mux_2_1  T1(A, B, C, Y5);
	Tabla2_Mux_2_1  T2(A, B, C, Y6);
	
	initial begin
	#1
	$display("");
	$display("<<<<<<<<<<<<<<<<<<<<<<<<<<<<<<IMPLEMENTACION MUX 8:1>>>>>>>>>>>>>>>>>>>>>>>>>>>>>>");
	$display("");
	$display("EJERCICIO 1: TABLA 1 ");
    $display("A B C | Y");
    $display("------|--");
    $monitor("%b %b %b | %b", A, B, C, Y1);
       A = 0; B = 0; C = 0;
    #1 A = 0; B = 0; C = 1;
    #1 A = 0; B = 1; C = 0;
    #1 A = 0; B = 1; C = 1;
    #1 A = 1; B = 0; C = 0;
    #1 A = 1; B = 0; C = 1;
    #1 A = 1; B = 1; C = 0;
    #1 A = 1; B = 1; C = 1;
	#1 $display("");
  end
  
	initial begin
	#10
	$display("EJERCICIO 1: TABLA 2 ");
    $display("A B C | Y");
    $display("------|--");
    $monitor("%b %b %b | %b", A, B, C, Y2);
       A = 0; B = 0; C = 0;
    #1 A = 0; B = 0; C = 1;
    #1 A = 0; B = 1; C = 0;
    #1 A = 0; B = 1; C = 1;
    #1 A = 1; B = 0; C = 0;
    #1 A = 1; B = 0; C = 1;
    #1 A = 1; B = 1; C = 0;
    #1 A = 1; B = 1; C = 1;
	#1 $display("");
  end
  
	initial begin
	#20
	$display("");
	$display("<<<<<<<<<<<<<<<<<<<<<<<<<<<<<<IMPLEMENTACION MUX 4:1>>>>>>>>>>>>>>>>>>>>>>>>>>>>>>");
	$display("");
	$display("EJERCICIO 1: TABLA 1 ");
    $display("A B C | Y");
    $display("------|--");
    $monitor("%b %b %b | %b", A, B, C, Y3);
       A = 0; B = 0; C = 0;
    #1 A = 0; B = 0; C = 1;
    #1 A = 0; B = 1; C = 0;
    #1 A = 0; B = 1; C = 1;
    #1 A = 1; B = 0; C = 0;
    #1 A = 1; B = 0; C = 1;
    #1 A = 1; B = 1; C = 0;
    #1 A = 1; B = 1; C = 1;
	#1 $display("");
  end
  
	initial begin
	#30
	$display("EJERCICIO 1: TABLA 2 ");
    $display("A B C | Y");
    $display("------|--");
    $monitor("%b %b %b | %b", A, B, C, Y4);
       A = 0; B = 0; C = 0;
    #1 A = 0; B = 0; C = 1;
    #1 A = 0; B = 1; C = 0;
    #1 A = 0; B = 1; C = 1;
    #1 A = 1; B = 0; C = 0;
    #1 A = 1; B = 0; C = 1;
    #1 A = 1; B = 1; C = 0;
    #1 A = 1; B = 1; C = 1;
	#1 $display("");
  end
  
	initial begin
	#40
	$display("");
	$display("<<<<<<<<<<<<<<<<<<<<<<<<<<<<<<IMPLEMENTACION MUX 2:1>>>>>>>>>>>>>>>>>>>>>>>>>>>>>>");
	$display("");
	$display("EJERCICIO 1: TABLA 1 ");
    $display("A B C | Y");
    $display("------|--");
    $monitor("%b %b %b | %b", A, B, C, Y5);
       A = 0; B = 0; C = 0;
    #1 A = 0; B = 0; C = 1;
    #1 A = 0; B = 1; C = 0;
    #1 A = 0; B = 1; C = 1;
    #1 A = 1; B = 0; C = 0;
    #1 A = 1; B = 0; C = 1;
    #1 A = 1; B = 1; C = 0;
    #1 A = 1; B = 1; C = 1;
	#1 $display("");
  end
  
	initial begin
	#50
	$display("EJERCICIO 1: TABLA 2 ");
    $display("A B C | Y");
    $display("------|--");
    $monitor("%b %b %b | %b", A, B, C, Y6);
       A = 0; B = 0; C = 0;
    #1 A = 0; B = 0; C = 1;
    #1 A = 0; B = 1; C = 0;
    #1 A = 0; B = 1; C = 1;
    #1 A = 1; B = 0; C = 0;
    #1 A = 1; B = 0; C = 1;
    #1 A = 1; B = 1; C = 0;
    #1 A = 1; B = 1; C = 1;
	#1 $display("");
  end
	
	
	initial
    #60	$finish;
	
  initial begin
    $dumpfile("Ejercicio4_tb.vcd");
    $dumpvars(0, testbench);
  end

endmodule

Ejercicio4_tb.vcd
$date
	Sat Aug 15 22:20:21 2020
$end
$version
	Icarus Verilog
$end
$timescale
	1ps
$end
$scope module testbench $end
$var wire 1 ! DG $end
$var wire 1 " DH $end
$var wire 1 # Y6 $end
$var wire 1 $ Y5 $end
$var wire 1 % Y4 $end
$var wire 1 & Y3 $end
$var wire 1 ' Y2 $end
$var wire 1 ( Y1 $end
$var reg 1 ) A $end
$var reg 1 * B $end
$var reg 1 + C $end
$scope module T1 $end
$var wire 1 ) A $end
$var wire 1 * B $end
$var wire 1 + C $end
$var wire 1 , D0 $end
$var wire 1 - D1 $end
$var wire 1 $ Y $end
$scope module T1 $end
$var wire 1 , D_0 $end
$var wire 1 - D_1 $end
$var wire 1 ) S_0 $end
$var wire 1 $ Y $end
$upscope $end
$upscope $end
$scope module T2 $end
$var wire 1 ) A $end
$var wire 1 * B $end
$var wire 1 + C $end
$var wire 1 . D0 $end
$var wire 1 / D1 $end
$var wire 1 # Y $end
$scope module T2 $end
$var wire 1 . D_0 $end
$var wire 1 / D_1 $end
$var wire 1 ) S_0 $end
$var wire 1 # Y $end
$upscope $end
$upscope $end
$scope module T_1 $end
$var wire 1 ) A $end
$var wire 1 * B $end
$var wire 1 + C $end
$var wire 1 ! D_0 $end
$var wire 1 " D_1 $end
$var wire 1 " D_2 $end
$var wire 1 ! D_3 $end
$var wire 1 " D_4 $end
$var wire 1 ! D_5 $end
$var wire 1 ! D_6 $end
$var wire 1 " D_7 $end
$var wire 1 ( Y $end
$scope module T1 $end
$var wire 1 ! D_0 $end
$var wire 1 " D_1 $end
$var wire 1 " D_2 $end
$var wire 1 ! D_3 $end
$var wire 1 " D_4 $end
$var wire 1 ! D_5 $end
$var wire 1 ! D_6 $end
$var wire 1 " D_7 $end
$var wire 1 + S_0 $end
$var wire 1 * S_1 $end
$var wire 1 ) S_2 $end
$var wire 1 0 Y4 $end
$var wire 1 1 Y3 $end
$var wire 1 2 Y2 $end
$var wire 1 3 Y1 $end
$var wire 1 ( Y $end
$scope module D0 $end
$var wire 1 ! D_0 $end
$var wire 1 " D_1 $end
$var wire 1 + S_0 $end
$var wire 1 3 Y $end
$upscope $end
$scope module D1 $end
$var wire 1 " D_0 $end
$var wire 1 ! D_1 $end
$var wire 1 + S_0 $end
$var wire 1 2 Y $end
$upscope $end
$scope module D2 $end
$var wire 1 " D_0 $end
$var wire 1 ! D_1 $end
$var wire 1 + S_0 $end
$var wire 1 1 Y $end
$upscope $end
$scope module D3 $end
$var wire 1 ! D_0 $end
$var wire 1 " D_1 $end
$var wire 1 + S_0 $end
$var wire 1 0 Y $end
$upscope $end
$scope module Out $end
$var wire 1 3 D_0 $end
$var wire 1 2 D_1 $end
$var wire 1 1 D_2 $end
$var wire 1 0 D_3 $end
$var wire 1 * S_0 $end
$var wire 1 ) S_1 $end
$var wire 1 4 Y2 $end
$var wire 1 5 Y1 $end
$var wire 1 ( Y $end
$scope module D0 $end
$var wire 1 3 D_0 $end
$var wire 1 2 D_1 $end
$var wire 1 * S_0 $end
$var wire 1 5 Y $end
$upscope $end
$scope module D1 $end
$var wire 1 1 D_0 $end
$var wire 1 0 D_1 $end
$var wire 1 * S_0 $end
$var wire 1 4 Y $end
$upscope $end
$scope module Out $end
$var wire 1 5 D_0 $end
$var wire 1 4 D_1 $end
$var wire 1 ) S_0 $end
$var wire 1 ( Y $end
$upscope $end
$upscope $end
$upscope $end
$upscope $end
$scope module T_2 $end
$var wire 1 ) A $end
$var wire 1 * B $end
$var wire 1 + C $end
$var wire 1 " D_0 $end
$var wire 1 ! D_1 $end
$var wire 1 ! D_2 $end
$var wire 1 ! D_3 $end
$var wire 1 ! D_4 $end
$var wire 1 " D_5 $end
$var wire 1 " D_6 $end
$var wire 1 ! D_7 $end
$var wire 1 ' Y $end
$scope module T2 $end
$var wire 1 " D_0 $end
$var wire 1 ! D_1 $end
$var wire 1 ! D_2 $end
$var wire 1 ! D_3 $end
$var wire 1 ! D_4 $end
$var wire 1 " D_5 $end
$var wire 1 " D_6 $end
$var wire 1 ! D_7 $end
$var wire 1 + S_0 $end
$var wire 1 * S_1 $end
$var wire 1 ) S_2 $end
$var wire 1 6 Y4 $end
$var wire 1 7 Y3 $end
$var wire 1 8 Y2 $end
$var wire 1 9 Y1 $end
$var wire 1 ' Y $end
$scope module D0 $end
$var wire 1 " D_0 $end
$var wire 1 ! D_1 $end
$var wire 1 + S_0 $end
$var wire 1 9 Y $end
$upscope $end
$scope module D1 $end
$var wire 1 ! D_0 $end
$var wire 1 ! D_1 $end
$var wire 1 + S_0 $end
$var wire 1 8 Y $end
$upscope $end
$scope module D2 $end
$var wire 1 ! D_0 $end
$var wire 1 " D_1 $end
$var wire 1 + S_0 $end
$var wire 1 7 Y $end
$upscope $end
$scope module D3 $end
$var wire 1 " D_0 $end
$var wire 1 ! D_1 $end
$var wire 1 + S_0 $end
$var wire 1 6 Y $end
$upscope $end
$scope module Out $end
$var wire 1 9 D_0 $end
$var wire 1 8 D_1 $end
$var wire 1 7 D_2 $end
$var wire 1 6 D_3 $end
$var wire 1 * S_0 $end
$var wire 1 ) S_1 $end
$var wire 1 : Y2 $end
$var wire 1 ; Y1 $end
$var wire 1 ' Y $end
$scope module D0 $end
$var wire 1 9 D_0 $end
$var wire 1 8 D_1 $end
$var wire 1 * S_0 $end
$var wire 1 ; Y $end
$upscope $end
$scope module D1 $end
$var wire 1 7 D_0 $end
$var wire 1 6 D_1 $end
$var wire 1 * S_0 $end
$var wire 1 : Y $end
$upscope $end
$scope module Out $end
$var wire 1 ; D_0 $end
$var wire 1 : D_1 $end
$var wire 1 ) S_0 $end
$var wire 1 ' Y $end
$upscope $end
$upscope $end
$upscope $end
$upscope $end
$scope module t_1 $end
$var wire 1 ) A $end
$var wire 1 * B $end
$var wire 1 + C $end
$var wire 1 < NC $end
$var wire 1 & Y $end
$scope module T1 $end
$var wire 1 + D_0 $end
$var wire 1 < D_1 $end
$var wire 1 < D_2 $end
$var wire 1 + D_3 $end
$var wire 1 * S_0 $end
$var wire 1 ) S_1 $end
$var wire 1 = Y2 $end
$var wire 1 > Y1 $end
$var wire 1 & Y $end
$scope module D0 $end
$var wire 1 + D_0 $end
$var wire 1 < D_1 $end
$var wire 1 * S_0 $end
$var wire 1 > Y $end
$upscope $end
$scope module D1 $end
$var wire 1 < D_0 $end
$var wire 1 + D_1 $end
$var wire 1 * S_0 $end
$var wire 1 = Y $end
$upscope $end
$scope module Out $end
$var wire 1 > D_0 $end
$var wire 1 = D_1 $end
$var wire 1 ) S_0 $end
$var wire 1 & Y $end
$upscope $end
$upscope $end
$upscope $end
$scope module t_2 $end
$var wire 1 ) A $end
$var wire 1 * B $end
$var wire 1 + C $end
$var wire 1 ! DG $end
$var wire 1 ? NC $end
$var wire 1 % Y $end
$scope module T2 $end
$var wire 1 ? D_0 $end
$var wire 1 ! D_1 $end
$var wire 1 + D_2 $end
$var wire 1 ? D_3 $end
$var wire 1 * S_0 $end
$var wire 1 ) S_1 $end
$var wire 1 @ Y2 $end
$var wire 1 A Y1 $end
$var wire 1 % Y $end
$scope module D0 $end
$var wire 1 ? D_0 $end
$var wire 1 ! D_1 $end
$var wire 1 * S_0 $end
$var wire 1 A Y $end
$upscope $end
$scope module D1 $end
$var wire 1 + D_0 $end
$var wire 1 ? D_1 $end
$var wire 1 * S_0 $end
$var wire 1 @ Y $end
$upscope $end
$scope module Out $end
$var wire 1 A D_0 $end
$var wire 1 @ D_1 $end
$var wire 1 ) S_0 $end
$var wire 1 % Y $end
$upscope $end
$upscope $end
$upscope $end
$upscope $end
$enddefinitions $end
#0
$dumpvars
xA
x@
x?
x>
x=
x<
x;
x:
x9
08
x7
x6
x5
x4
x3
x2
x1
x0
x/
x.
x-
x,
x+
x*
x)
x(
x'
x&
x%
x$
x#
1"
0!
$end
#1
0(
1'
1%
05
14
1;
0:
1=
1A
1-
0$
1#
0&
03
12
11
00
19
07
16
1<
1?
0,
1.
1/
0>
0@
0+
0*
0)
#2
1(
0'
0%
0-
1$
0#
15
04
0;
1:
0=
1&
0A
1,
0.
13
02
01
10
09
17
06
0<
1>
0?
1@
1+
#3
1(
1&
03
12
11
00
19
07
16
1<
1?
15
04
1:
1>
1@
0+
1*
#4
0(
0&
1-
0$
05
14
0:
0>
0@
0,
0/
13
02
01
10
09
17
06
0<
1=
0?
1+
#5
1;
1A
1#
0'
03
12
11
00
19
07
16
1<
1?
1.
1/
05
14
0:
1=
1$
1(
1&
0+
0*
1)
#6
0$
0(
1'
0&
0-
15
04
0;
1:
0=
0A
1%
1,
0.
13
02
01
10
09
17
06
0<
1>
0?
1@
1+
#7
0(
1'
1%
03
12
11
00
19
07
16
1<
1?
15
04
1:
1>
1@
0+
1*
#8
1$
1(
0'
0%
1-
0#
05
14
0:
0>
1&
0@
0,
0/
13
02
01
10
09
17
06
0<
1=
0?
1+
#10
1'
1%
1;
1A
1#
03
12
11
00
19
07
16
1<
1?
1.
1/
05
14
0:
1=
0$
0(
0&
0+
0*
0)
#11
1(
0'
0%
0-
1$
0#
15
04
0;
1:
0=
1&
0A
1,
0.
13
02
01
10
09
17
06
0<
1>
0?
1@
1+
#12
1(
1&
03
12
11
00
19
07
16
1<
1?
15
04
1:
1>
1@
0+
1*
#13
0(
0&
1-
0$
05
14
0:
0>
0@
0,
0/
13
02
01
10
09
17
06
0<
1=
0?
1+
#14
1;
1A
1#
0'
03
12
11
00
19
07
16
1<
1?
1.
1/
05
14
0:
1=
1$
1(
1&
0+
0*
1)
#15
0$
0(
1'
0&
0-
15
04
0;
1:
0=
0A
1%
1,
0.
13
02
01
10
09
17
06
0<
1>
0?
1@
1+
#16
0(
1'
1%
03
12
11
00
19
07
16
1<
1?
15
04
1:
1>
1@
0+
1*
#17
1$
1(
0'
0%
1-
0#
05
14
0:
0>
1&
0@
0,
0/
13
02
01
10
09
17
06
0<
1=
0?
1+
#20
1'
1%
1;
1A
1#
03
12
11
00
19
07
16
1<
1?
1.
1/
05
14
0:
1=
0$
0(
0&
0+
0*
0)
#21
1(
0'
0%
0-
1$
0#
15
04
0;
1:
0=
1&
0A
1,
0.
13
02
01
10
09
17
06
0<
1>
0?
1@
1+
#22
1(
1&
03
12
11
00
19
07
16
1<
1?
15
04
1:
1>
1@
0+
1*
#23
0(
0&
1-
0$
05
14
0:
0>
0@
0,
0/
13
02
01
10
09
17
06
0<
1=
0?
1+
#24
1;
1A
1#
0'
03
12
11
00
19
07
16
1<
1?
1.
1/
05
14
0:
1=
1$
1(
1&
0+
0*
1)
#25
0$
0(
1'
0&
0-
15
04
0;
1:
0=
0A
1%
1,
0.
13
02
01
10
09
17
06
0<
1>
0?
1@
1+
#26
0(
1'
1%
03
12
11
00
19
07
16
1<
1?
15
04
1:
1>
1@
0+
1*
#27
1$
1(
0'
0%
1-
0#
05
14
0:
0>
1&
0@
0,
0/
13
02
01
10
09
17
06
0<
1=
0?
1+
#30
1'
1%
1;
1A
1#
03
12
11
00
19
07
16
1<
1?
1.
1/
05
14
0:
1=
0$
0(
0&
0+
0*
0)
#31
1(
0'
0%
0-
1$
0#
15
04
0;
1:
0=
1&
0A
1,
0.
13
02
01
10
09
17
06
0<
1>
0?
1@
1+
#32
1(
1&
03
12
11
00
19
07
16
1<
1?
15
04
1:
1>
1@
0+
1*
#33
0(
0&
1-
0$
05
14
0:
0>
0@
0,
0/
13
02
01
10
09
17
06
0<
1=
0?
1+
#34
1;
1A
1#
0'
03
12
11
00
19
07
16
1<
1?
1.
1/
05
14
0:
1=
1$
1(
1&
0+
0*
1)
#35
0$
0(
1'
0&
0-
15
04
0;
1:
0=
0A
1%
1,
0.
13
02
01
10
09
17
06
0<
1>
0?
1@
1+
#36
0(
1'
1%
03
12
11
00
19
07
16
1<
1?
15
04
1:
1>
1@
0+
1*
#37
1$
1(
0'
0%
1-
0#
05
14
0:
0>
1&
0@
0,
0/
13
02
01
10
09
17
06
0<
1=
0?
1+
#40
1'
1%
1;
1A
1#
03
12
11
00
19
07
16
1<
1?
1.
1/
05
14
0:
1=
0$
0(
0&
0+
0*
0)
#41
1(
0'
0%
0-
1$
0#
15
04
0;
1:
0=
1&
0A
1,
0.
13
02
01
10
09
17
06
0<
1>
0?
1@
1+
#42
1(
1&
03
12
11
00
19
07
16
1<
1?
15
04
1:
1>
1@
0+
1*
#43
0(
0&
1-
0$
05
14
0:
0>
0@
0,
0/
13
02
01
10
09
17
06
0<
1=
0?
1+
#44
1;
1A
1#
0'
03
12
11
00
19
07
16
1<
1?
1.
1/
05
14
0:
1=
1$
1(
1&
0+
0*
1)
#45
0$
0(
1'
0&
0-
15
04
0;
1:
0=
0A
1%
1,
0.
13
02
01
10
09
17
06
0<
1>
0?
1@
1+
#46
0(
1'
1%
03
12
11
00
19
07
16
1<
1?
15
04
1:
1>
1@
0+
1*
#47
1$
1(
0'
0%
1-
0#
05
14
0:
0>
1&
0@
0,
0/
13
02
01
10
09
17
06
0<
1=
0?
1+
#50
1'
1%
1;
1A
1#
03
12
11
00
19
07
16
1<
1?
1.
1/
05
14
0:
1=
0$
0(
0&
0+
0*
0)
#51
1(
0'
0%
0-
1$
0#
15
04
0;
1:
0=
1&
0A
1,
0.
13
02
01
10
09
17
06
0<
1>
0?
1@
1+
#52
1(
1&
03
12
11
00
19
07
16
1<
1?
15
04
1:
1>
1@
0+
1*
#53
0(
0&
1-
0$
05
14
0:
0>
0@
0,
0/
13
02
01
10
09
17
06
0<
1=
0?
1+
#54
1;
1A
1#
0'
03
12
11
00
19
07
16
1<
1?
1.
1/
05
14
0:
1=
1$
1(
1&
0+
0*
1)
#55
0$
0(
1'
0&
0-
15
04
0;
1:
0=
0A
1%
1,
0.
13
02
01
10
09
17
06
0<
1>
0?
1@
1+
#56
0(
1'
1%
03
12
11
00
19
07
16
1<
1?
15
04
1:
1>
1@
0+
1*
#57
1$
1(
0'
0%
1-
0#
05
14
0:
0>
1&
0@
0,
0/
13
02
01
10
09
17
06
0<
1=
0?
1+
